MANIFEST.in
README.rst
setup.cfg
setup.py
src/harness/__init__.py
src/harness/config.py
src/harness/grpc.proto
src/harness/grpc_pb2.py
src/harness/http.proto
src/harness/http_pb2.py
src/harness/logging.proto
src/harness/logging_pb2.py
src/harness/metrics.proto
src/harness/metrics_pb2.py
src/harness/net.proto
src/harness/net_pb2.py
src/harness/postgres.proto
src/harness/postgres_pb2.py
src/harness/redis.proto
src/harness/redis_pb2.py
src/harness/tracing.proto
src/harness/tracing_pb2.py
src/harness/wire.proto
src/harness/wire_pb2.py
src/harness.egg-info/PKG-INFO
src/harness.egg-info/SOURCES.txt
src/harness.egg-info/dependency_links.txt
src/harness.egg-info/entry_points.txt
src/harness.egg-info/requires.txt
src/harness.egg-info/top_level.txt
src/harness/cli/__init__.py
src/harness/cli/check.py
src/harness/cli/kubegen.py
src/harness/cli/main.py
src/harness/cli/protopath.py
src/harness/cli/utils.py
src/harness/plugin/__init__.py
src/harness/plugin/main.py
src/harness/plugin/python.py
src/harness/runtime/__init__.py
src/harness/runtime/_features.py
src/harness/runtime/_runner.py
src/harness/runtime/_utils.py
src/harness/runtime/_validate.py
src/harness/wires/__init__.py
src/harness/wires/aiomonitor.py
src/harness/wires/asyncpg.py
src/harness/wires/base.py
src/harness/wires/logging.py
src/harness/wires/prometheus.py
src/harness/wires/aiohttp/__init__.py
src/harness/wires/aiohttp/web.py
src/harness/wires/apscheduler/__init__.py
src/harness/wires/apscheduler/jobstores/__init__.py
src/harness/wires/apscheduler/jobstores/redis.py
src/harness/wires/grpclib/__init__.py
src/harness/wires/grpclib/client.py
src/harness/wires/grpclib/server.py
src/harness/wires/opentelemetry/__init__.py
src/harness/wires/opentelemetry/ext/__init__.py
src/harness/wires/opentelemetry/ext/jaeger.py
src/harness/wires/opentelemetry/ext/prometheus.py
src/validate/__init__.py
src/validate/validate.proto
src/validate/validate_pb2.py