Metadata-Version: 2.1
Name: harness
Version: 0.1.0
Summary: Language-neutral meta-framework for server-less style services
Home-page: https://github.com/vmagamedov/harness
Author: Vladimir Magamedov
Author-email: vladimir@magamedov.com
License: BSD-3-Clause
Platform: UNKNOWN
Classifier: Development Status :: 4 - Beta
Classifier: Intended Audience :: Developers
Classifier: License :: OSI Approved :: BSD License
Classifier: Operating System :: OS Independent
Classifier: Programming Language :: Python
Classifier: Programming Language :: Python :: 3.7
Classifier: Programming Language :: Python :: 3.8
Classifier: Programming Language :: Python :: 3 :: Only
Requires-Python: >=3.7
Provides-Extra: sdk
